gym_recorder/__init__.py
gym_recorder/const.py
gym_recorder/recorder.py
gym_record-0.0.3.dist-info/LICENCE
gym_record-0.0.3.dist-info/METADATA
gym_record-0.0.3.dist-info/WHEEL
gym_record-0.0.3.dist-info/top_level.txt
gym_record-0.0.3.dist-info/RECORD
