Metadata-Version: 2.1
Name: gym-record
Version: 0.0.3
Summary: A recorder for open ai gym. you can easily add a text on the frame
Home-page: https://github.com/gyuta/gym_recorder
Author: gyuta
License: UNKNOWN
Project-URL: Bug Tracker, https://github.com/gyuta/gym_recorder/issues
Platform: UNKNOWN
Classifier: Programming Language :: Python :: 3
Classifier: License :: OSI Approved :: MIT License
Classifier: Operating System :: OS Independent
License-File: LICENCE
Requires-Dist: gym
Requires-Dist: opencv-python
